{
  "api": {
    "dataset": "production",
    "projectId": "dki5l4zp"
  },
  "parts": [
    {
      "name": "part:@sanity/base/schema",
      "path": "./schemas/schema.js"
    },
    {
      "name": "part:@sanity/desk-tool/structure",
      "path": "./structure/desk-structure.js"
    }
  ],
  "plugins": [
    "@sanity/base",
    "@sanity/components",
    "@sanity/default-layout",
    "@sanity/default-login",
    "@sanity/desk-tool",
    "@sanity/color-input",
    "@sanity/code-input"
  ],
  "project": {
    "name": "Website Factory Starter"
  },
  "root": true
}
